{
  "snapshot_at": "2026-05-29T12:30:01-03:00",
  "snapshot_label": "12h30 BRT",
  "trading_date": "2026-05-29",
  "schema_version": "1.1",
  "ativos": {
    "WIN1!": {
      "error": "range_check_failed: 174335 fora da faixa [180000, 200000]",
      "last_raw": 174335
    },
    "WDO1!": {
      "error": "range_check_failed: 5099.5 fora da faixa [4800, 5050]",
      "last_raw": 5099.5
    },
    "DXY": {
      "symbol": "TVC:DXY",
      "last": 98.817,
      "last_time": 1780066800,
      "open_first": 99.095,
      "range_50_high": 99.544,
      "range_50_low": 98.776,
      "change_abs": -0.425,
      "change_pct": -0.43,
      "pos_in_range_pct": 5,
      "vol_last": 0
    },
    "USDJPY": {
      "symbol": "PEPPERSTONE:USDJPY",
      "last": 159.176,
      "last_time": 1780066800,
      "open_first": 159.384,
      "range_50_high": 159.654,
      "range_50_low": 159.095,
      "change_abs": -0.334,
      "change_pct": -0.21,
      "pos_in_range_pct": 14,
      "vol_last": 8103
    },
    "US500": {
      "symbol": "PEPPERSTONE:US500",
      "last": 7590.4,
      "last_time": 1780066800,
      "open_first": 7540.5,
      "range_50_high": 7601.6,
      "range_50_low": 7495.7,
      "change_abs": 48.4,
      "change_pct": 0.64,
      "pos_in_range_pct": 89,
      "vol_last": 5096
    },
    "NAS100": {
      "error": "range_check_failed: 30365.7 fora da faixa [22000, 30000]",
      "last_raw": 30365.7
    },
    "XAUUSD": {
      "symbol": "PEPPERSTONE:XAUUSD",
      "last": 4579.78,
      "last_time": 1780066800,
      "open_first": 4428.96,
      "range_50_high": 4595,
      "range_50_low": 4366.29,
      "change_abs": 140.81,
      "change_pct": 3.17,
      "pos_in_range_pct": 93,
      "vol_last": 14444
    }
  },
  "macro": {
    "di_curve_eod_investing": {
      "source": "investing.com",
      "fetched_at": "2026-05-29T15:30:31.781Z",
      "eod": true,
      "yields": {
        "1y": {
          "last": 13.78,
          "prev_close": 13.78,
          "change_bps": 0
        },
        "2y": {
          "last": 13.725,
          "prev_close": 13.725,
          "change_bps": 0
        },
        "3y": {
          "last": 13.72,
          "prev_close": 13.72,
          "change_bps": 0
        },
        "5y": {
          "last": 13.908,
          "prev_close": 13.908,
          "change_bps": 0
        },
        "10y": {
          "last": 14.105,
          "prev_close": 14.105,
          "change_bps": 0
        }
      },
      "parsed": 5
    }
  }
}