{
  "snapshot_at": "2026-05-13T08:30:01-03:00",
  "snapshot_label": "08h30 BRT",
  "trading_date": "2026-05-13",
  "schema_version": "1.1",
  "ativos": {
    "WIN1!": {
      "symbol": "BMFBOVESPA:WIN1!",
      "last": 182725,
      "last_time": 1778619600,
      "open_first": 191440,
      "range_50_high": 192560,
      "range_50_low": 182145,
      "change_abs": -8665,
      "change_pct": -4.53,
      "pos_in_range_pct": 6,
      "vol_last": 126264,
      "daily_prev_close": {
        "time": 1778587200,
        "close": 182673,
        "date_iso": "2026-05-12"
      }
    },
    "WDO1!": {
      "symbol": "BMFBOVESPA:WDO1!",
      "last": 4914,
      "last_time": 1778619600,
      "open_first": 4915,
      "range_50_high": 4964.5,
      "range_50_low": 4910,
      "change_abs": -42.5,
      "change_pct": -0.86,
      "pos_in_range_pct": 7,
      "vol_last": 19617,
      "daily_prev_close": {
        "time": 1778587200,
        "close": 4915.913,
        "date_iso": "2026-05-12"
      }
    },
    "DXY": {
      "symbol": "TVC:DXY",
      "last": 98.469,
      "last_time": 1778670000,
      "open_first": 98.023,
      "range_50_high": 98.588,
      "range_50_low": 97.85,
      "change_abs": 0.455,
      "change_pct": 0.46,
      "pos_in_range_pct": 84,
      "vol_last": 0
    },
    "USDJPY": {
      "symbol": "PEPPERSTONE:USDJPY",
      "last": 157.792,
      "last_time": 1778670000,
      "open_first": 157.144,
      "range_50_high": 157.897,
      "range_50_low": 156.749,
      "change_abs": 0.649,
      "change_pct": 0.41,
      "pos_in_range_pct": 91,
      "vol_last": 3812
    },
    "US500": {
      "symbol": "PEPPERSTONE:US500",
      "last": 7422.8,
      "last_time": 1778670000,
      "open_first": 7395.5,
      "range_50_high": 7436.3,
      "range_50_low": 7345.3,
      "change_abs": 27.5,
      "change_pct": 0.37,
      "pos_in_range_pct": 85,
      "vol_last": 2128
    },
    "NAS100": {
      "symbol": "PEPPERSTONE:NAS100",
      "last": 29280.9,
      "last_time": 1778670000,
      "open_first": 29239.2,
      "range_50_high": 29395.5,
      "range_50_low": 28661.4,
      "change_abs": 67.5,
      "change_pct": 0.23,
      "pos_in_range_pct": 84,
      "vol_last": 10208
    },
    "XAUUSD": {
      "symbol": "PEPPERSTONE:XAUUSD",
      "last": 4700.11,
      "last_time": 1778670000,
      "open_first": 4667.83,
      "range_50_high": 4773.53,
      "range_50_low": 4638.17,
      "change_abs": 32.42,
      "change_pct": 0.69,
      "pos_in_range_pct": 46,
      "vol_last": 9749
    }
  },
  "macro": {
    "di_curve_eod_investing": {
      "source": "investing.com",
      "fetched_at": "2026-05-13T11:30:39.265Z",
      "eod": true,
      "yields": {
        "1y": {
          "last": 13.85,
          "prev_close": 13.85,
          "change_bps": 0
        },
        "2y": {
          "last": 13.78,
          "prev_close": 13.78,
          "change_bps": 0
        },
        "3y": {
          "last": 13.752,
          "prev_close": 13.752,
          "change_bps": 0
        },
        "5y": {
          "last": 13.882,
          "prev_close": 13.882,
          "change_bps": 0
        },
        "10y": {
          "last": 14.047,
          "prev_close": 14.047,
          "change_bps": 0
        }
      },
      "parsed": 5
    }
  }
}